{
  "matchInfo": {
    "id": "FB4800",
    "home": "Bournemouth",
    "away": "Tottenham",
    "date": "2024-12-06",
    "matchKey": "FB4800_2024-12-06_Bournemouth_vs_Tottenham"
  },
  "analysis": {
    "totalSnapshots": 71,
    "timeSpan": {
      "start": "2024-12-04T17:34:04.297Z",
      "end": "2024-12-05T21:57:57.225Z",
      "durationMinutes": 1703.8821333333333
    },
    "handicapMovements": [
      {
        "from": 0,
        "to": 0.25,
        "change": 0.25,
        "time": "2024-12-05T05:03:57.341Z"
      },
      {
        "from": 0.25,
        "to": 0,
        "change": -0.25,
        "time": "2024-12-05T09:48:58.267Z"
      },
      {
        "from": 0,
        "to": 0.25,
        "change": 0.25,
        "time": "2024-12-05T19:07:01.621Z"
      },
      {
        "from": 0.25,
        "to": 0,
        "change": -0.25,
        "time": "2024-12-05T20:25:57.112Z"
      },
      {
        "from": 0,
        "to": 0.75,
        "change": 0.75,
        "time": "2024-12-05T20:34:57.515Z"
      },
      {
        "from": 0.75,
        "to": 1,
        "change": 0.25,
        "time": "2024-12-05T21:26:57.864Z"
      },
      {
        "from": 1,
        "to": 0.75,
        "change": -0.25,
        "time": "2024-12-05T21:30:58.050Z"
      },
      {
        "from": 0.75,
        "to": 1,
        "change": 0.25,
        "time": "2024-12-05T21:46:58.756Z"
      }
    ],
    "oddsMovements": [
      {
        "from": 1.92,
        "to": 1.98,
        "change": 0.06000000000000005,
        "changePercent": "3.13",
        "time": "2024-12-05T04:57:57.058Z"
      },
      {
        "from": 2.03,
        "to": 2.09,
        "change": 0.06000000000000005,
        "changePercent": "2.96",
        "time": "2024-12-05T05:01:57.241Z"
      },
      {
        "from": 2.09,
        "to": 1.85,
        "change": -0.23999999999999977,
        "changePercent": "-11.48",
        "time": "2024-12-05T05:03:57.341Z"
      },
      {
        "from": 1.85,
        "to": 1.8,
        "change": -0.050000000000000044,
        "changePercent": "-2.70",
        "time": "2024-12-05T05:37:58.844Z"
      },
      {
        "from": 1.8,
        "to": 1.75,
        "change": -0.050000000000000044,
        "changePercent": "-2.78",
        "time": "2024-12-05T07:38:58.601Z"
      },
      {
        "from": 1.75,
        "to": 2.03,
        "change": 0.2799999999999998,
        "changePercent": "16.00",
        "time": "2024-12-05T09:48:58.267Z"
      },
      {
        "from": 2.03,
        "to": 2.08,
        "change": 0.050000000000000266,
        "changePercent": "2.46",
        "time": "2024-12-05T12:23:59.184Z"
      },
      {
        "from": 2.08,
        "to": 2.14,
        "change": 0.06000000000000005,
        "changePercent": "2.88",
        "time": "2024-12-05T19:05:03.532Z"
      },
      {
        "from": 2.14,
        "to": 1.9,
        "change": -0.2400000000000002,
        "changePercent": "-11.21",
        "time": "2024-12-05T19:07:01.621Z"
      },
      {
        "from": 1.75,
        "to": 1.95,
        "change": 0.19999999999999996,
        "changePercent": "11.43",
        "time": "2024-12-05T20:25:57.112Z"
      },
      {
        "from": 1.95,
        "to": 1.9,
        "change": -0.050000000000000044,
        "changePercent": "-2.56",
        "time": "2024-12-05T20:29:23.260Z"
      },
      {
        "from": 1.9,
        "to": 1.99,
        "change": 0.09000000000000008,
        "changePercent": "4.74",
        "time": "2024-12-05T20:34:57.515Z"
      },
      {
        "from": 2,
        "to": 1.92,
        "change": -0.08000000000000007,
        "changePercent": "-4.00",
        "time": "2024-12-05T20:36:57.598Z"
      },
      {
        "from": 2.08,
        "to": 1.67,
        "change": -0.41000000000000014,
        "changePercent": "-19.71",
        "time": "2024-12-05T21:26:57.864Z"
      },
      {
        "from": 1.67,
        "to": 2.01,
        "change": 0.33999999999999986,
        "changePercent": "20.36",
        "time": "2024-12-05T21:30:58.050Z"
      },
      {
        "from": 2.01,
        "to": 2.2,
        "change": 0.1900000000000004,
        "changePercent": "9.45",
        "time": "2024-12-05T21:44:58.672Z"
      },
      {
        "from": 2.25,
        "to": 1.59,
        "change": -0.6599999999999999,
        "changePercent": "-29.33",
        "time": "2024-12-05T21:46:58.756Z"
      },
      {
        "from": 1.6,
        "to": 1.73,
        "change": 0.1299999999999999,
        "changePercent": "8.12",
        "time": "2024-12-05T21:49:56.881Z"
      },
      {
        "from": 1.79,
        "to": 1.84,
        "change": 0.050000000000000044,
        "changePercent": "2.79",
        "time": "2024-12-05T21:57:57.225Z"
      }
    ],
    "patterns": {
      "handicapStability": false,
      "oddsVolatility": "HIGH",
      "trappedInQuarter": false,
      "significantSwings": [
        {
          "type": "SHORTENING",
          "magnitude": 0.23999999999999977,
          "from": 2.09,
          "to": 1.85,
          "time": "2024-12-05T05:03:57.341Z"
        },
        {
          "type": "LENGTHENING",
          "magnitude": 0.2799999999999998,
          "from": 1.75,
          "to": 2.03,
          "time": "2024-12-05T09:48:58.267Z"
        },
        {
          "type": "SHORTENING",
          "magnitude": 0.2400000000000002,
          "from": 2.14,
          "to": 1.9,
          "time": "2024-12-05T19:07:01.621Z"
        },
        {
          "type": "LENGTHENING",
          "magnitude": 0.19999999999999996,
          "from": 1.75,
          "to": 1.95,
          "time": "2024-12-05T20:25:57.112Z"
        },
        {
          "type": "SHORTENING",
          "magnitude": 0.41000000000000014,
          "from": 2.08,
          "to": 1.67,
          "time": "2024-12-05T21:26:57.864Z"
        },
        {
          "type": "LENGTHENING",
          "magnitude": 0.33999999999999986,
          "from": 1.67,
          "to": 2.01,
          "time": "2024-12-05T21:30:58.050Z"
        },
        {
          "type": "LENGTHENING",
          "magnitude": 0.1900000000000004,
          "from": 2.01,
          "to": 2.2,
          "time": "2024-12-05T21:44:58.672Z"
        },
        {
          "type": "SHORTENING",
          "magnitude": 0.6599999999999999,
          "from": 2.25,
          "to": 1.59,
          "time": "2024-12-05T21:46:58.756Z"
        }
      ]
    }
  },
  "oddsTimeline": [
    {
      "timestamp": 1733333644297,
      "readableDate": "2024-12-04T17:34:04.297Z",
      "ahHome": 0,
      "ahAway": 0,
      "oddsHome": 1.9,
      "oddsAway": 1.86,
      "originalRecord": {
        "id": "FB4800",
        "home": "Bournemouth",
        "away": "Tottenham",
        "date": "2024-12-06",
        "ahHome": 0,
        "ahAway": 0,
        "oddsHome": 1.9,
        "oddsAway": 1.86,
        "ts": 1733333644289
      }
    },
    {
      "timestamp": 1733334908287,
      "readableDate": "2024-12-04T17:55:08.287Z",
      "ahHome": 0,
      "ahAway": 0,
      "oddsHome": 1.9,
      "oddsAway": 1.86,
      "originalRecord": {
        "id": "FB4800",
        "home": "Bournemouth",
        "away": "Tottenham",
        "date": "2024-12-06",
        "ahHome": 0,
        "ahAway": 0,
        "oddsHome": 1.9,
        "oddsAway": 1.86,
        "ts": 1733334908275
      }
    },
    {
      "timestamp": 1733335004480,
      "readableDate": "2024-12-04T17:56:44.480Z",
      "ahHome": 0,
      "ahAway": 0,
      "oddsHome": 1.9,
      "oddsAway": 1.86,
      "originalRecord": {
        "id": "FB4800",
        "home": "Bournemouth",
        "away": "Tottenham",
        "date": "2024-12-06",
        "ahHome": 0,
        "ahAway": 0,
        "oddsHome": 1.9,
        "oddsAway": 1.86,
        "ts": 1733335004455
      }
    },
    {
      "timestamp": 1733335082900,
      "readableDate": "2024-12-04T17:58:02.900Z",
      "ahHome": 0,
      "ahAway": 0,
      "oddsHome": 1.9,
      "oddsAway": 1.86,
      "originalRecord": {
        "id": "FB4800",
        "home": "Bournemouth",
        "away": "Tottenham",
        "date": "2024-12-06",
        "ahHome": 0,
        "ahAway": 0,
        "oddsHome": 1.9,
        "oddsAway": 1.86,
        "ts": 1733335082892
      }
    },
    {
      "timestamp": 1733335109964,
      "readableDate": "2024-12-04T17:58:29.964Z",
      "ahHome": 0,
      "ahAway": 0,
      "oddsHome": 1.9,
      "oddsAway": 1.86,
      "originalRecord": {
        "id": "FB4800",
        "home": "Bournemouth",
        "away": "Tottenham",
        "date": "2024-12-06",
        "ahHome": 0,
        "ahAway": 0,
        "oddsHome": 1.9,
        "oddsAway": 1.86,
        "ts": 1733335109956
      }
    },
    {
      "timestamp": 1733335181978,
      "readableDate": "2024-12-04T17:59:41.978Z",
      "ahHome": 0,
      "ahAway": 0,
      "oddsHome": 1.9,
      "oddsAway": 1.86,
      "originalRecord": {
        "id": "FB4800",
        "home": "Bournemouth",
        "away": "Tottenham",
        "date": "2024-12-06",
        "ahHome": 0,
        "ahAway": 0,
        "oddsHome": 1.9,
        "oddsAway": 1.86,
        "ts": 1733335181972
      }
    },
    {
      "timestamp": 1733335232343,
      "readableDate": "2024-12-04T18:00:32.343Z",
      "ahHome": 0,
      "ahAway": 0,
      "oddsHome": 1.9,
      "oddsAway": 1.86,
      "originalRecord": {
        "id": "FB4800",
        "home": "Bournemouth",
        "away": "Tottenham",
        "date": "2024-12-06",
        "ahHome": 0,
        "ahAway": 0,
        "oddsHome": 1.9,
        "oddsAway": 1.86,
        "ts": 1733335232338
      }
    },
    {
      "timestamp": 1733335292773,
      "readableDate": "2024-12-04T18:01:32.773Z",
      "ahHome": 0,
      "ahAway": 0,
      "oddsHome": 1.9,
      "oddsAway": 1.86,
      "originalRecord": {
        "id": "FB4800",
        "home": "Bournemouth",
        "away": "Tottenham",
        "date": "2024-12-06",
        "ahHome": 0,
        "ahAway": 0,
        "oddsHome": 1.9,
        "oddsAway": 1.86,
        "ts": 1733335292747
      }
    },
    {
      "timestamp": 1733335401019,
      "readableDate": "2024-12-04T18:03:21.019Z",
      "ahHome": 0,
      "ahAway": 0,
      "oddsHome": 1.9,
      "oddsAway": 1.86,
      "originalRecord": {
        "id": "FB4800",
        "home": "Bournemouth",
        "away": "Tottenham",
        "date": "2024-12-06",
        "ahHome": 0,
        "ahAway": 0,
        "oddsHome": 1.9,
        "oddsAway": 1.86,
        "ts": 1733335401007
      }
    },
    {
      "timestamp": 1733335739568,
      "readableDate": "2024-12-04T18:08:59.568Z",
      "ahHome": 0,
      "ahAway": 0,
      "oddsHome": 1.9,
      "oddsAway": 1.86,
      "originalRecord": {
        "id": "FB4800",
        "home": "Bournemouth",
        "away": "Tottenham",
        "date": "2024-12-06",
        "ahHome": 0,
        "ahAway": 0,
        "oddsHome": 1.9,
        "oddsAway": 1.86,
        "ts": 1733335739560
      }
    },
    {
      "timestamp": 1733335785461,
      "readableDate": "2024-12-04T18:09:45.461Z",
      "ahHome": 0,
      "ahAway": 0,
      "oddsHome": 1.9,
      "oddsAway": 1.86,
      "originalRecord": {
        "id": "FB4800",
        "home": "Bournemouth",
        "away": "Tottenham",
        "date": "2024-12-06",
        "ahHome": 0,
        "ahAway": 0,
        "oddsHome": 1.9,
        "oddsAway": 1.86,
        "ts": 1733335785454
      }
    },
    {
      "timestamp": 1733335818129,
      "readableDate": "2024-12-04T18:10:18.129Z",
      "ahHome": 0,
      "ahAway": 0,
      "oddsHome": 1.9,
      "oddsAway": 1.86,
      "originalRecord": {
        "id": "FB4800",
        "home": "Bournemouth",
        "away": "Tottenham",
        "date": "2024-12-06",
        "ahHome": 0,
        "ahAway": 0,
        "oddsHome": 1.9,
        "oddsAway": 1.86,
        "ts": 1733335818123
      }
    },
    {
      "timestamp": 1733335852299,
      "readableDate": "2024-12-04T18:10:52.299Z",
      "ahHome": 0,
      "ahAway": 0,
      "oddsHome": 1.9,
      "oddsAway": 1.86,
      "originalRecord": {
        "id": "FB4800",
        "home": "Bournemouth",
        "away": "Tottenham",
        "date": "2024-12-06",
        "ahHome": 0,
        "ahAway": 0,
        "oddsHome": 1.9,
        "oddsAway": 1.86,
        "ts": 1733335852293
      }
    },
    {
      "timestamp": 1733336136108,
      "readableDate": "2024-12-04T18:15:36.108Z",
      "ahHome": 0,
      "ahAway": 0,
      "oddsHome": 1.9,
      "oddsAway": 1.86,
      "originalRecord": {
        "id": "FB4800",
        "home": "Bournemouth",
        "away": "Tottenham",
        "date": "2024-12-06",
        "ahHome": 0,
        "ahAway": 0,
        "oddsHome": 1.9,
        "oddsAway": 1.86,
        "ts": 1733336136102
      }
    },
    {
      "timestamp": 1733336223100,
      "readableDate": "2024-12-04T18:17:03.100Z",
      "ahHome": 0,
      "ahAway": 0,
      "oddsHome": 1.9,
      "oddsAway": 1.86,
      "originalRecord": {
        "id": "FB4800",
        "home": "Bournemouth",
        "away": "Tottenham",
        "date": "2024-12-06",
        "ahHome": 0,
        "ahAway": 0,
        "oddsHome": 1.9,
        "oddsAway": 1.86,
        "ts": 1733336223090
      }
    },
    {
      "timestamp": 1733372097157,
      "readableDate": "2024-12-05T04:14:57.157Z",
      "ahHome": 0,
      "ahAway": 0,
      "oddsHome": 1.94,
      "oddsAway": 1.88,
      "originalRecord": {
        "id": "FB4800",
        "home": "Bournemouth",
        "away": "Tottenham",
        "date": "2024-12-06",
        "ahHome": 0,
        "ahAway": 0,
        "oddsHome": 1.94,
        "oddsAway": 1.88,
        "ts": 1733372097157
      }
    },
    {
      "timestamp": 1733373238000,
      "readableDate": "2024-12-05T04:33:58.000Z",
      "ahHome": 0,
      "ahAway": 0,
      "oddsHome": 1.92,
      "oddsAway": 1.9,
      "originalRecord": {
        "id": "FB4800",
        "home": "Bournemouth",
        "away": "Tottenham",
        "date": "2024-12-06",
        "ahHome": 0,
        "ahAway": 0,
        "oddsHome": 1.92,
        "oddsAway": 1.9,
        "ts": 1733373237998
      }
    },
    {
      "timestamp": 1733373538205,
      "readableDate": "2024-12-05T04:38:58.205Z",
      "ahHome": 0,
      "ahAway": 0,
      "oddsHome": 1.9,
      "oddsAway": 1.92,
      "originalRecord": {
        "id": "FB4800",
        "home": "Bournemouth",
        "away": "Tottenham",
        "date": "2024-12-06",
        "ahHome": 0,
        "ahAway": 0,
        "oddsHome": 1.9,
        "oddsAway": 1.92,
        "ts": 1733373538205
      }
    },
    {
      "timestamp": 1733374677058,
      "readableDate": "2024-12-05T04:57:57.058Z",
      "ahHome": 0,
      "ahAway": 0,
      "oddsHome": 1.84,
      "oddsAway": 1.98,
      "originalRecord": {
        "id": "FB4800",
        "home": "Bournemouth",
        "away": "Tottenham",
        "date": "2024-12-06",
        "ahHome": 0,
        "ahAway": 0,
        "oddsHome": 1.84,
        "oddsAway": 1.98,
        "ts": 1733374677056
      }
    },
    {
      "timestamp": 1733374737102,
      "readableDate": "2024-12-05T04:58:57.102Z",
      "ahHome": 0,
      "ahAway": 0,
      "oddsHome": 1.8,
      "oddsAway": 2.03,
      "originalRecord": {
        "id": "FB4800",
        "home": "Bournemouth",
        "away": "Tottenham",
        "date": "2024-12-06",
        "ahHome": 0,
        "ahAway": 0,
        "oddsHome": 1.8,
        "oddsAway": 2.03,
        "ts": 1733374737101
      }
    },
    {
      "timestamp": 1733374917241,
      "readableDate": "2024-12-05T05:01:57.241Z",
      "ahHome": 0,
      "ahAway": 0,
      "oddsHome": 1.75,
      "oddsAway": 2.09,
      "originalRecord": {
        "id": "FB4800",
        "home": "Bournemouth",
        "away": "Tottenham",
        "date": "2024-12-06",
        "ahHome": 0,
        "ahAway": 0,
        "oddsHome": 1.75,
        "oddsAway": 2.09,
        "ts": 1733374917240
      }
    },
    {
      "timestamp": 1733375037341,
      "readableDate": "2024-12-05T05:03:57.341Z",
      "ahHome": -0.25,
      "ahAway": 0.25,
      "oddsHome": 1.97,
      "oddsAway": 1.85,
      "originalRecord": {
        "id": "FB4800",
        "home": "Bournemouth",
        "away": "Tottenham",
        "date": "2024-12-06",
        "ahHome": -0.25,
        "ahAway": 0.25,
        "oddsHome": 1.97,
        "oddsAway": 1.85,
        "ts": 1733375037339
      }
    },
    {
      "timestamp": 1733377078844,
      "readableDate": "2024-12-05T05:37:58.844Z",
      "ahHome": -0.25,
      "ahAway": 0.25,
      "oddsHome": 2.03,
      "oddsAway": 1.8,
      "originalRecord": {
        "id": "FB4800",
        "home": "Bournemouth",
        "away": "Tottenham",
        "date": "2024-12-06",
        "ahHome": -0.25,
        "ahAway": 0.25,
        "oddsHome": 2.03,
        "oddsAway": 1.8,
        "ts": 1733377078842
      }
    },
    {
      "timestamp": 1733384338601,
      "readableDate": "2024-12-05T07:38:58.601Z",
      "ahHome": -0.25,
      "ahAway": 0.25,
      "oddsHome": 2.1,
      "oddsAway": 1.75,
      "originalRecord": {
        "id": "FB4800",
        "home": "Bournemouth",
        "away": "Tottenham",
        "date": "2024-12-06",
        "ahHome": -0.25,
        "ahAway": 0.25,
        "oddsHome": 2.1,
        "oddsAway": 1.75,
        "ts": 1733384338597
      }
    },
    {
      "timestamp": 1733392138267,
      "readableDate": "2024-12-05T09:48:58.267Z",
      "ahHome": 0,
      "ahAway": 0,
      "oddsHome": 1.8,
      "oddsAway": 2.03,
      "originalRecord": {
        "id": "FB4800",
        "home": "Bournemouth",
        "away": "Tottenham",
        "date": "2024-12-06",
        "ahHome": 0,
        "ahAway": 0,
        "oddsHome": 1.8,
        "oddsAway": 2.03,
        "ts": 1733392138265
      }
    },
    {
      "timestamp": 1733401439184,
      "readableDate": "2024-12-05T12:23:59.184Z",
      "ahHome": 0,
      "ahAway": 0,
      "oddsHome": 1.76,
      "oddsAway": 2.08,
      "originalRecord": {
        "id": "FB4800",
        "home": "Bournemouth",
        "away": "Tottenham",
        "date": "2024-12-06",
        "ahHome": 0,
        "ahAway": 0,
        "oddsHome": 1.76,
        "oddsAway": 2.08,
        "ts": 1733401439181
      }
    },
    {
      "timestamp": 1733416438280,
      "readableDate": "2024-12-05T16:33:58.280Z",
      "ahHome": 0,
      "ahAway": 0,
      "oddsHome": 1.79,
      "oddsAway": 2.04,
      "originalRecord": {
        "id": "FB4800",
        "home": "Bournemouth",
        "away": "Tottenham",
        "date": "2024-12-06",
        "ahHome": 0,
        "ahAway": 0,
        "oddsHome": 1.79,
        "oddsAway": 2.04,
        "ts": 1733416438278
      }
    },
    {
      "timestamp": 1733425377430,
      "readableDate": "2024-12-05T19:02:57.430Z",
      "ahHome": 0,
      "ahAway": 0,
      "oddsHome": 1.76,
      "oddsAway": 2.08,
      "originalRecord": {
        "id": "FB4800",
        "home": "Bournemouth",
        "away": "Tottenham",
        "date": "2024-12-06",
        "ahHome": 0,
        "ahAway": 0,
        "oddsHome": 1.76,
        "oddsAway": 2.08,
        "ts": 1733425377430
      }
    },
    {
      "timestamp": 1733425503532,
      "readableDate": "2024-12-05T19:05:03.532Z",
      "ahHome": 0,
      "ahAway": 0,
      "oddsHome": 1.72,
      "oddsAway": 2.14,
      "originalRecord": {
        "id": "FB4800",
        "home": "Bournemouth",
        "away": "Tottenham",
        "date": "2024-12-06",
        "ahHome": 0,
        "ahAway": 0,
        "oddsHome": 1.72,
        "oddsAway": 2.14,
        "ts": 1733425503531
      }
    },
    {
      "timestamp": 1733425621621,
      "readableDate": "2024-12-05T19:07:01.621Z",
      "ahHome": -0.25,
      "ahAway": 0.25,
      "oddsHome": 1.92,
      "oddsAway": 1.9,
      "originalRecord": {
        "id": "FB4800",
        "home": "Bournemouth",
        "away": "Tottenham",
        "date": "2024-12-06",
        "ahHome": -0.25,
        "ahAway": 0.25,
        "oddsHome": 1.92,
        "oddsAway": 1.9,
        "ts": 1733425621621
      }
    },
    {
      "timestamp": 1733426097973,
      "readableDate": "2024-12-05T19:14:57.973Z",
      "ahHome": -0.25,
      "ahAway": 0.25,
      "oddsHome": 1.94,
      "oddsAway": 1.88,
      "originalRecord": {
        "id": "FB4800",
        "home": "Bournemouth",
        "away": "Tottenham",
        "date": "2024-12-06",
        "ahHome": -0.25,
        "ahAway": 0.25,
        "oddsHome": 1.94,
        "oddsAway": 1.88,
        "ts": 1733426097972
      }
    },
    {
      "timestamp": 1733427238839,
      "readableDate": "2024-12-05T19:33:58.839Z",
      "ahHome": -0.25,
      "ahAway": 0.25,
      "oddsHome": 1.91,
      "oddsAway": 1.91,
      "originalRecord": {
        "id": "FB4800",
        "home": "Bournemouth",
        "away": "Tottenham",
        "date": "2024-12-06",
        "ahHome": -0.25,
        "ahAway": 0.25,
        "oddsHome": 1.91,
        "oddsAway": 1.91,
        "ts": 1733427238839
      }
    },
    {
      "timestamp": 1733428497679,
      "readableDate": "2024-12-05T19:54:57.679Z",
      "ahHome": -0.25,
      "ahAway": 0.25,
      "oddsHome": 1.93,
      "oddsAway": 1.89,
      "originalRecord": {
        "id": "FB4800",
        "home": "Bournemouth",
        "away": "Tottenham",
        "date": "2024-12-06",
        "ahHome": -0.25,
        "ahAway": 0.25,
        "oddsHome": 1.93,
        "oddsAway": 1.89,
        "ts": 1733428497679
      }
    },
    {
      "timestamp": 1733429758661,
      "readableDate": "2024-12-05T20:15:58.661Z",
      "ahHome": -0.25,
      "ahAway": 0.25,
      "oddsHome": 1.88,
      "oddsAway": 1.84,
      "originalRecord": {
        "id": "FB4800",
        "home": "Bournemouth",
        "away": "Tottenham",
        "date": "2024-12-06",
        "ahHome": -0.25,
        "ahAway": 0.25,
        "oddsHome": 1.88,
        "oddsAway": 1.84,
        "ts": 1733429758659,
        "homeScore": "0",
        "awayScore": "0",
        "totalCorner": "0",
        "live": "1st"
      }
    },
    {
      "timestamp": 1733429938791,
      "readableDate": "2024-12-05T20:18:58.791Z",
      "ahHome": -0.25,
      "ahAway": 0.25,
      "oddsHome": 1.92,
      "oddsAway": 1.8,
      "originalRecord": {
        "id": "FB4800",
        "home": "Bournemouth",
        "away": "Tottenham",
        "date": "2024-12-06",
        "ahHome": -0.25,
        "ahAway": 0.25,
        "oddsHome": 1.92,
        "oddsAway": 1.8,
        "ts": 1733429938788,
        "homeScore": "0",
        "awayScore": "0",
        "totalCorner": "0",
        "live": "1st"
      }
    },
    {
      "timestamp": 1733430178976,
      "readableDate": "2024-12-05T20:22:58.976Z",
      "ahHome": -0.25,
      "ahAway": 0.25,
      "oddsHome": 1.94,
      "oddsAway": 1.79,
      "originalRecord": {
        "id": "FB4800",
        "home": "Bournemouth",
        "away": "Tottenham",
        "date": "2024-12-06",
        "ahHome": -0.25,
        "ahAway": 0.25,
        "oddsHome": 1.94,
        "oddsAway": 1.79,
        "ts": 1733430178976,
        "homeScore": "0",
        "awayScore": "0",
        "totalCorner": "---",
        "live": "1st"
      }
    },
    {
      "timestamp": 1733430297068,
      "readableDate": "2024-12-05T20:24:57.068Z",
      "ahHome": -0.25,
      "ahAway": 0.25,
      "oddsHome": 1.99,
      "oddsAway": 1.75,
      "originalRecord": {
        "id": "FB4800",
        "home": "Bournemouth",
        "away": "Tottenham",
        "date": "2024-12-06",
        "ahHome": -0.25,
        "ahAway": 0.25,
        "oddsHome": 1.99,
        "oddsAway": 1.75,
        "ts": 1733430297068,
        "homeScore": "0",
        "awayScore": "0",
        "totalCorner": "0",
        "live": "1st"
      }
    },
    {
      "timestamp": 1733430357112,
      "readableDate": "2024-12-05T20:25:57.112Z",
      "ahHome": 0,
      "ahAway": 0,
      "oddsHome": 1.78,
      "oddsAway": 1.95,
      "originalRecord": {
        "id": "FB4800",
        "home": "Bournemouth",
        "away": "Tottenham",
        "date": "2024-12-06",
        "ahHome": 0,
        "ahAway": 0,
        "oddsHome": 1.78,
        "oddsAway": 1.95,
        "ts": 1733430357112,
        "homeScore": "0",
        "awayScore": "0",
        "totalCorner": "---",
        "live": "1st"
      }
    },
    {
      "timestamp": 1733430563260,
      "readableDate": "2024-12-05T20:29:23.260Z",
      "ahHome": 0,
      "ahAway": 0,
      "oddsHome": 1.82,
      "oddsAway": 1.9,
      "originalRecord": {
        "id": "FB4800",
        "home": "Bournemouth",
        "away": "Tottenham",
        "date": "2024-12-06",
        "ahHome": 0,
        "ahAway": 0,
        "oddsHome": 1.82,
        "oddsAway": 1.9,
        "ts": 1733430563260,
        "homeScore": "0",
        "awayScore": "0",
        "totalCorner": "1",
        "live": "1st"
      }
    },
    {
      "timestamp": 1733430897515,
      "readableDate": "2024-12-05T20:34:57.515Z",
      "ahHome": -0.75,
      "ahAway": 0.75,
      "oddsHome": 1.75,
      "oddsAway": 1.99,
      "originalRecord": {
        "id": "FB4800",
        "home": "Bournemouth",
        "away": "Tottenham",
        "date": "2024-12-06",
        "ahHome": -0.75,
        "ahAway": 0.75,
        "oddsHome": 1.75,
        "oddsAway": 1.99,
        "ts": 1733430897513,
        "homeScore": "1",
        "awayScore": "0",
        "totalCorner": "3",
        "live": "1st"
      }
    },
    {
      "timestamp": 1733430959562,
      "readableDate": "2024-12-05T20:35:59.562Z",
      "ahHome": -0.75,
      "ahAway": 0.75,
      "oddsHome": 1.74,
      "oddsAway": 2,
      "originalRecord": {
        "id": "FB4800",
        "home": "Bournemouth",
        "away": "Tottenham",
        "date": "2024-12-06",
        "ahHome": -0.75,
        "ahAway": 0.75,
        "oddsHome": 1.74,
        "oddsAway": 2,
        "ts": 1733430959561,
        "homeScore": "1",
        "awayScore": "0",
        "totalCorner": "3",
        "live": "1st"
      }
    },
    {
      "timestamp": 1733431017598,
      "readableDate": "2024-12-05T20:36:57.598Z",
      "ahHome": -0.75,
      "ahAway": 0.75,
      "oddsHome": 1.8,
      "oddsAway": 1.92,
      "originalRecord": {
        "id": "FB4800",
        "home": "Bournemouth",
        "away": "Tottenham",
        "date": "2024-12-06",
        "ahHome": -0.75,
        "ahAway": 0.75,
        "oddsHome": 1.8,
        "oddsAway": 1.92,
        "ts": 1733431017598,
        "homeScore": "1",
        "awayScore": "0",
        "totalCorner": "3",
        "live": "1st"
      }
    },
    {
      "timestamp": 1733431199742,
      "readableDate": "2024-12-05T20:39:59.742Z",
      "ahHome": -0.75,
      "ahAway": 0.75,
      "oddsHome": 1.82,
      "oddsAway": 1.9,
      "originalRecord": {
        "id": "FB4800",
        "home": "Bournemouth",
        "away": "Tottenham",
        "date": "2024-12-06",
        "ahHome": -0.75,
        "ahAway": 0.75,
        "oddsHome": 1.82,
        "oddsAway": 1.9,
        "ts": 1733431199741,
        "homeScore": "1",
        "awayScore": "0",
        "totalCorner": "3",
        "live": "1st"
      }
    },
    {
      "timestamp": 1733431381887,
      "readableDate": "2024-12-05T20:43:01.887Z",
      "ahHome": -0.75,
      "ahAway": 0.75,
      "oddsHome": 1.81,
      "oddsAway": 1.91,
      "originalRecord": {
        "id": "FB4800",
        "home": "Bournemouth",
        "away": "Tottenham",
        "date": "2024-12-06",
        "ahHome": -0.75,
        "ahAway": 0.75,
        "oddsHome": 1.81,
        "oddsAway": 1.91,
        "ts": 1733431381887,
        "homeScore": "1",
        "awayScore": "0",
        "totalCorner": "---",
        "live": "1st"
      }
    },
    {
      "timestamp": 1733431497980,
      "readableDate": "2024-12-05T20:44:57.980Z",
      "ahHome": -0.75,
      "ahAway": 0.75,
      "oddsHome": 1.8,
      "oddsAway": 1.92,
      "originalRecord": {
        "id": "FB4800",
        "home": "Bournemouth",
        "away": "Tottenham",
        "date": "2024-12-06",
        "ahHome": -0.75,
        "ahAway": 0.75,
        "oddsHome": 1.8,
        "oddsAway": 1.92,
        "ts": 1733431497980,
        "homeScore": "1",
        "awayScore": "0",
        "totalCorner": "4",
        "live": "1st"
      }
    },
    {
      "timestamp": 1733431618071,
      "readableDate": "2024-12-05T20:46:58.071Z",
      "ahHome": -0.75,
      "ahAway": 0.75,
      "oddsHome": 1.79,
      "oddsAway": 1.94,
      "originalRecord": {
        "id": "FB4800",
        "home": "Bournemouth",
        "away": "Tottenham",
        "date": "2024-12-06",
        "ahHome": -0.75,
        "ahAway": 0.75,
        "oddsHome": 1.79,
        "oddsAway": 1.94,
        "ts": 1733431618070,
        "homeScore": "1",
        "awayScore": "0",
        "totalCorner": "4",
        "live": "1st"
      }
    },
    {
      "timestamp": 1733431858258,
      "readableDate": "2024-12-05T20:50:58.258Z",
      "ahHome": -0.75,
      "ahAway": 0.75,
      "oddsHome": 1.78,
      "oddsAway": 1.95,
      "originalRecord": {
        "id": "FB4800",
        "home": "Bournemouth",
        "away": "Tottenham",
        "date": "2024-12-06",
        "ahHome": -0.75,
        "ahAway": 0.75,
        "oddsHome": 1.78,
        "oddsAway": 1.95,
        "ts": 1733431858258,
        "homeScore": "1",
        "awayScore": "0",
        "totalCorner": "4",
        "live": "1st"
      }
    },
    {
      "timestamp": 1733432038395,
      "readableDate": "2024-12-05T20:53:58.395Z",
      "ahHome": -0.75,
      "ahAway": 0.75,
      "oddsHome": 1.77,
      "oddsAway": 1.96,
      "originalRecord": {
        "id": "FB4800",
        "home": "Bournemouth",
        "away": "Tottenham",
        "date": "2024-12-06",
        "ahHome": -0.75,
        "ahAway": 0.75,
        "oddsHome": 1.77,
        "oddsAway": 1.96,
        "ts": 1733432038393,
        "homeScore": "1",
        "awayScore": "0",
        "totalCorner": "---",
        "live": "1st"
      }
    },
    {
      "timestamp": 1733432098431,
      "readableDate": "2024-12-05T20:54:58.431Z",
      "ahHome": -0.75,
      "ahAway": 0.75,
      "oddsHome": 1.76,
      "oddsAway": 1.97,
      "originalRecord": {
        "id": "FB4800",
        "home": "Bournemouth",
        "away": "Tottenham",
        "date": "2024-12-06",
        "ahHome": -0.75,
        "ahAway": 0.75,
        "oddsHome": 1.76,
        "oddsAway": 1.97,
        "ts": 1733432098431,
        "homeScore": "1",
        "awayScore": "0",
        "totalCorner": "6",
        "live": "1st"
      }
    },
    {
      "timestamp": 1733432278555,
      "readableDate": "2024-12-05T20:57:58.555Z",
      "ahHome": -0.75,
      "ahAway": 0.75,
      "oddsHome": 1.75,
      "oddsAway": 1.99,
      "originalRecord": {
        "id": "FB4800",
        "home": "Bournemouth",
        "away": "Tottenham",
        "date": "2024-12-06",
        "ahHome": -0.75,
        "ahAway": 0.75,
        "oddsHome": 1.75,
        "oddsAway": 1.99,
        "ts": 1733432278555,
        "homeScore": "1",
        "awayScore": "0",
        "totalCorner": "6",
        "live": "1st"
      }
    },
    {
      "timestamp": 1733432458691,
      "readableDate": "2024-12-05T21:00:58.691Z",
      "ahHome": -0.75,
      "ahAway": 0.75,
      "oddsHome": 1.73,
      "oddsAway": 2.01,
      "originalRecord": {
        "id": "FB4800",
        "home": "Bournemouth",
        "away": "Tottenham",
        "date": "2024-12-06",
        "ahHome": -0.75,
        "ahAway": 0.75,
        "oddsHome": 1.73,
        "oddsAway": 2.01,
        "ts": 1733432458691,
        "homeScore": "1",
        "awayScore": "0",
        "totalCorner": "6",
        "live": "1st"
      }
    },
    {
      "timestamp": 1733432638818,
      "readableDate": "2024-12-05T21:03:58.818Z",
      "ahHome": -0.75,
      "ahAway": 0.75,
      "oddsHome": 1.72,
      "oddsAway": 2.02,
      "originalRecord": {
        "id": "FB4800",
        "home": "Bournemouth",
        "away": "Tottenham",
        "date": "2024-12-06",
        "ahHome": -0.75,
        "ahAway": 0.75,
        "oddsHome": 1.72,
        "oddsAway": 2.02,
        "ts": 1733432638817,
        "homeScore": "1",
        "awayScore": "0",
        "totalCorner": "6",
        "live": "HT"
      }
    },
    {
      "timestamp": 1733433477456,
      "readableDate": "2024-12-05T21:17:57.456Z",
      "ahHome": -0.75,
      "ahAway": 0.75,
      "oddsHome": 1.71,
      "oddsAway": 2.02,
      "originalRecord": {
        "id": "FB4800",
        "home": "Bournemouth",
        "away": "Tottenham",
        "date": "2024-12-06",
        "ahHome": -0.75,
        "ahAway": 0.75,
        "oddsHome": 1.71,
        "oddsAway": 2.02,
        "ts": 1733433477456,
        "homeScore": "1",
        "awayScore": "0",
        "totalCorner": "6",
        "live": "2nd"
      }
    },
    {
      "timestamp": 1733433657592,
      "readableDate": "2024-12-05T21:20:57.592Z",
      "ahHome": -0.75,
      "ahAway": 0.75,
      "oddsHome": 1.7,
      "oddsAway": 2.05,
      "originalRecord": {
        "id": "FB4800",
        "home": "Bournemouth",
        "away": "Tottenham",
        "date": "2024-12-06",
        "ahHome": -0.75,
        "ahAway": 0.75,
        "oddsHome": 1.7,
        "oddsAway": 2.05,
        "ts": 1733433657592,
        "homeScore": "1",
        "awayScore": "0",
        "totalCorner": "6",
        "live": "2nd"
      }
    },
    {
      "timestamp": 1733433777678,
      "readableDate": "2024-12-05T21:22:57.678Z",
      "ahHome": -0.75,
      "ahAway": 0.75,
      "oddsHome": 1.69,
      "oddsAway": 2.07,
      "originalRecord": {
        "id": "FB4800",
        "home": "Bournemouth",
        "away": "Tottenham",
        "date": "2024-12-06",
        "ahHome": -0.75,
        "ahAway": 0.75,
        "oddsHome": 1.69,
        "oddsAway": 2.07,
        "ts": 1733433777677,
        "homeScore": "1",
        "awayScore": "0",
        "totalCorner": "7",
        "live": "2nd"
      }
    },
    {
      "timestamp": 1733433837720,
      "readableDate": "2024-12-05T21:23:57.720Z",
      "ahHome": -0.75,
      "ahAway": 0.75,
      "oddsHome": 1.68,
      "oddsAway": 2.08,
      "originalRecord": {
        "id": "FB4800",
        "home": "Bournemouth",
        "away": "Tottenham",
        "date": "2024-12-06",
        "ahHome": -0.75,
        "ahAway": 0.75,
        "oddsHome": 1.68,
        "oddsAway": 2.08,
        "ts": 1733433837719,
        "homeScore": "1",
        "awayScore": "0",
        "totalCorner": "---",
        "live": "2nd"
      }
    },
    {
      "timestamp": 1733434017864,
      "readableDate": "2024-12-05T21:26:57.864Z",
      "ahHome": -1,
      "ahAway": 1,
      "oddsHome": 2.1,
      "oddsAway": 1.67,
      "originalRecord": {
        "id": "FB4800",
        "home": "Bournemouth",
        "away": "Tottenham",
        "date": "2024-12-06",
        "ahHome": -1,
        "ahAway": 1,
        "oddsHome": 2.1,
        "oddsAway": 1.67,
        "ts": 1733434017864,
        "homeScore": "1",
        "awayScore": "0",
        "totalCorner": "8",
        "live": "2nd"
      }
    },
    {
      "timestamp": 1733434258050,
      "readableDate": "2024-12-05T21:30:58.050Z",
      "ahHome": -0.75,
      "ahAway": 0.75,
      "oddsHome": 1.73,
      "oddsAway": 2.01,
      "originalRecord": {
        "id": "FB4800",
        "home": "Bournemouth",
        "away": "Tottenham",
        "date": "2024-12-06",
        "ahHome": -0.75,
        "ahAway": 0.75,
        "oddsHome": 1.73,
        "oddsAway": 2.01,
        "ts": 1733434258050,
        "homeScore": "1",
        "awayScore": "0",
        "totalCorner": "9",
        "live": "2nd"
      }
    },
    {
      "timestamp": 1733434318097,
      "readableDate": "2024-12-05T21:31:58.097Z",
      "ahHome": -0.75,
      "ahAway": 0.75,
      "oddsHome": 1.74,
      "oddsAway": 1.99,
      "originalRecord": {
        "id": "FB4800",
        "home": "Bournemouth",
        "away": "Tottenham",
        "date": "2024-12-06",
        "ahHome": -0.75,
        "ahAway": 0.75,
        "oddsHome": 1.74,
        "oddsAway": 1.99,
        "ts": 1733434318097,
        "homeScore": "1",
        "awayScore": "0",
        "totalCorner": "9",
        "live": "2nd"
      }
    },
    {
      "timestamp": 1733434438176,
      "readableDate": "2024-12-05T21:33:58.176Z",
      "ahHome": -0.75,
      "ahAway": 0.75,
      "oddsHome": 1.72,
      "oddsAway": 2.02,
      "originalRecord": {
        "id": "FB4800",
        "home": "Bournemouth",
        "away": "Tottenham",
        "date": "2024-12-06",
        "ahHome": -0.75,
        "ahAway": 0.75,
        "oddsHome": 1.72,
        "oddsAway": 2.02,
        "ts": 1733434438176,
        "homeScore": "1",
        "awayScore": "0",
        "totalCorner": "9",
        "live": "2nd"
      }
    },
    {
      "timestamp": 1733434618320,
      "readableDate": "2024-12-05T21:36:58.320Z",
      "ahHome": -0.75,
      "ahAway": 0.75,
      "oddsHome": 1.75,
      "oddsAway": 1.98,
      "originalRecord": {
        "id": "FB4800",
        "home": "Bournemouth",
        "away": "Tottenham",
        "date": "2024-12-06",
        "ahHome": -0.75,
        "ahAway": 0.75,
        "oddsHome": 1.75,
        "oddsAway": 1.98,
        "ts": 1733434618319,
        "homeScore": "1",
        "awayScore": "0",
        "totalCorner": "10",
        "live": "2nd"
      }
    },
    {
      "timestamp": 1733434858507,
      "readableDate": "2024-12-05T21:40:58.507Z",
      "ahHome": -0.75,
      "ahAway": 0.75,
      "oddsHome": 1.73,
      "oddsAway": 2.01,
      "originalRecord": {
        "id": "FB4800",
        "home": "Bournemouth",
        "away": "Tottenham",
        "date": "2024-12-06",
        "ahHome": -0.75,
        "ahAway": 0.75,
        "oddsHome": 1.73,
        "oddsAway": 2.01,
        "ts": 1733434858507,
        "homeScore": "1",
        "awayScore": "0",
        "totalCorner": "---",
        "live": "2nd"
      }
    },
    {
      "timestamp": 1733435098672,
      "readableDate": "2024-12-05T21:44:58.672Z",
      "ahHome": -0.75,
      "ahAway": 0.75,
      "oddsHome": 1.61,
      "oddsAway": 2.2,
      "originalRecord": {
        "id": "FB4800",
        "home": "Bournemouth",
        "away": "Tottenham",
        "date": "2024-12-06",
        "ahHome": -0.75,
        "ahAway": 0.75,
        "oddsHome": 1.61,
        "oddsAway": 2.2,
        "ts": 1733435098671,
        "homeScore": "1",
        "awayScore": "0",
        "totalCorner": "12",
        "live": "2nd"
      }
    },
    {
      "timestamp": 1733435158709,
      "readableDate": "2024-12-05T21:45:58.709Z",
      "ahHome": -0.75,
      "ahAway": 0.75,
      "oddsHome": 1.58,
      "oddsAway": 2.25,
      "originalRecord": {
        "id": "FB4800",
        "home": "Bournemouth",
        "away": "Tottenham",
        "date": "2024-12-06",
        "ahHome": -0.75,
        "ahAway": 0.75,
        "oddsHome": 1.58,
        "oddsAway": 2.25,
        "ts": 1733435158708,
        "homeScore": "1",
        "awayScore": "0",
        "totalCorner": "12",
        "live": "2nd"
      }
    },
    {
      "timestamp": 1733435218756,
      "readableDate": "2024-12-05T21:46:58.756Z",
      "ahHome": -1,
      "ahAway": 1,
      "oddsHome": 2.22,
      "oddsAway": 1.59,
      "originalRecord": {
        "id": "FB4800",
        "home": "Bournemouth",
        "away": "Tottenham",
        "date": "2024-12-06",
        "ahHome": -1,
        "ahAway": 1,
        "oddsHome": 2.22,
        "oddsAway": 1.59,
        "ts": 1733435218756,
        "homeScore": "1",
        "awayScore": "0",
        "totalCorner": "12",
        "live": "2nd"
      }
    },
    {
      "timestamp": 1733435278801,
      "readableDate": "2024-12-05T21:47:58.801Z",
      "ahHome": -1,
      "ahAway": 1,
      "oddsHome": 2.21,
      "oddsAway": 1.6,
      "originalRecord": {
        "id": "FB4800",
        "home": "Bournemouth",
        "away": "Tottenham",
        "date": "2024-12-06",
        "ahHome": -1,
        "ahAway": 1,
        "oddsHome": 2.21,
        "oddsAway": 1.6,
        "ts": 1733435278801,
        "homeScore": "1",
        "awayScore": "0",
        "totalCorner": "12",
        "live": "2nd"
      }
    },
    {
      "timestamp": 1733435396881,
      "readableDate": "2024-12-05T21:49:56.881Z",
      "ahHome": -1,
      "ahAway": 1,
      "oddsHome": 2.01,
      "oddsAway": 1.73,
      "originalRecord": {
        "id": "FB4800",
        "home": "Bournemouth",
        "away": "Tottenham",
        "date": "2024-12-06",
        "ahHome": -1,
        "ahAway": 1,
        "oddsHome": 2.01,
        "oddsAway": 1.73,
        "ts": 1733435396880,
        "homeScore": "1",
        "awayScore": "0",
        "totalCorner": "12",
        "live": "2nd"
      }
    },
    {
      "timestamp": 1733435516970,
      "readableDate": "2024-12-05T21:51:56.970Z",
      "ahHome": -1,
      "ahAway": 1,
      "oddsHome": 1.98,
      "oddsAway": 1.75,
      "originalRecord": {
        "id": "FB4800",
        "home": "Bournemouth",
        "away": "Tottenham",
        "date": "2024-12-06",
        "ahHome": -1,
        "ahAway": 1,
        "oddsHome": 1.98,
        "oddsAway": 1.75,
        "ts": 1733435516970,
        "homeScore": "1",
        "awayScore": "0",
        "totalCorner": "12",
        "live": "2nd"
      }
    },
    {
      "timestamp": 1733435699113,
      "readableDate": "2024-12-05T21:54:59.113Z",
      "ahHome": -1,
      "ahAway": 1,
      "oddsHome": 1.94,
      "oddsAway": 1.78,
      "originalRecord": {
        "id": "FB4800",
        "home": "Bournemouth",
        "away": "Tottenham",
        "date": "2024-12-06",
        "ahHome": -1,
        "ahAway": 1,
        "oddsHome": 1.94,
        "oddsAway": 1.78,
        "ts": 1733435699113,
        "homeScore": "1",
        "awayScore": "0",
        "totalCorner": "12",
        "live": "2nd"
      }
    },
    {
      "timestamp": 1733435817179,
      "readableDate": "2024-12-05T21:56:57.179Z",
      "ahHome": -1,
      "ahAway": 1,
      "oddsHome": 1.93,
      "oddsAway": 1.79,
      "originalRecord": {
        "id": "FB4800",
        "home": "Bournemouth",
        "away": "Tottenham",
        "date": "2024-12-06",
        "ahHome": -1,
        "ahAway": 1,
        "oddsHome": 1.93,
        "oddsAway": 1.79,
        "ts": 1733435817178,
        "homeScore": "1",
        "awayScore": "0",
        "totalCorner": "12",
        "live": "2nd"
      }
    },
    {
      "timestamp": 1733435877225,
      "readableDate": "2024-12-05T21:57:57.225Z",
      "ahHome": -1,
      "ahAway": 1,
      "oddsHome": 1.88,
      "oddsAway": 1.84,
      "originalRecord": {
        "id": "FB4800",
        "home": "Bournemouth",
        "away": "Tottenham",
        "date": "2024-12-06",
        "ahHome": -1,
        "ahAway": 1,
        "oddsHome": 1.88,
        "oddsAway": 1.84,
        "ts": 1733435877225,
        "homeScore": "1",
        "awayScore": "0",
        "totalCorner": "---",
        "live": "2nd"
      }
    }
  ],
  "exportMetadata": {
    "exportedAt": "2025-06-26T17:11:21.418Z",
    "totalSnapshots": 71,
    "dataQuality": "CLEAN_PRE_MATCH_ONLY"
  }
}