{
  "strategy": {
    "name": "Adaptive_CrossRule_ahLine_x_ahHomeOdds_Plus_preMatch_enhanced_marketEfficiency",
    "roi": "0.00%",
    "correlation": "0.0609",
    "factors": [
      "parseFloat(match.asianHandicapOdds.homeHandicap.split('/')[0])",
      "match.asianHandicapOdds.homeOdds",
      "preMatch.enhanced.marketEfficiency"
    ],
    "hypothesis": "Extending successful CrossRule_ahLine_x_ahHomeOdds with preMatch.enhanced.marketEfficiency",
    "error": null
  },
  "summary": {
    "totalBets": 0,
    "totalProfit": 0,
    "winRate": "0%",
    "generatedAt": "2025-06-25T14:07:44.115Z"
  },
  "bettingRecords": []
}